lnt_sovereign/__init__.py
lnt_sovereign/cli.py
lnt_sovereign/client.py
lnt_sovereign/core/__init__.py
lnt_sovereign/core/agents.py
lnt_sovereign/core/analytics.py
lnt_sovereign/core/bias.py
lnt_sovereign/core/compiler.py
lnt_sovereign/core/dashboard.py
lnt_sovereign/core/database.py
lnt_sovereign/core/exceptions.py
lnt_sovereign/core/feedback.py
lnt_sovereign/core/formal.py
lnt_sovereign/core/generator.py
lnt_sovereign/core/jit_kernel.py
lnt_sovereign/core/kernel.py
lnt_sovereign/core/monitor.py
lnt_sovereign/core/nano_inference.py
lnt_sovereign/core/neural.py
lnt_sovereign/core/optimized_kernel.py
lnt_sovereign/core/scale.py
lnt_sovereign/core/state.py
lnt_sovereign/core/telemetry.py
lnt_sovereign/core/topology.py
lnt_sovereign/manifests/examples/credit_score_v1.json
lnt_sovereign/manifests/examples/crs_profile.json
lnt_sovereign/manifests/examples/healthcare_triage.json
lnt_sovereign/manifests/examples/visa_application.json
lnt_sovereign-1.0.5.dist-info/licenses/LICENSE
lnt_sovereign-1.0.5.dist-info/METADATA
lnt_sovereign-1.0.5.dist-info/WHEEL
lnt_sovereign-1.0.5.dist-info/entry_points.txt
lnt_sovereign-1.0.5.dist-info/top_level.txt
lnt_sovereign-1.0.5.dist-info/RECORD
