Metadata-Version: 2.4
Name: lnt-sovereign
Version: 1.0.5
Summary: High-performance neuro-symbolic verification layer for AI validation and logic-based guardrails.
Author-email: wassmi <algasim.w@gmail.com>
License: MIT
Project-URL: Homepage, https://github.com/wassmi/lnt-sovereign
Project-URL: Bug Tracker, https://github.com/wassmi/lnt-sovereign/issues
Classifier: Programming Language :: Python :: 3
Classifier: License :: OSI Approved :: MIT License
Classifier: Operating System :: OS Independent
Classifier: Topic :: Scientific/Engineering :: Artificial Intelligence
Classifier: Topic :: Security :: Cryptography
Requires-Python: >=3.10
License-File: LICENSE
Requires-Dist: fastapi
Requires-Dist: uvicorn
Requires-Dist: pydantic>=2.0
Requires-Dist: numpy
Requires-Dist: numba
Requires-Dist: sqlalchemy
Requires-Dist: httpx
Requires-Dist: z3-solver
Requires-Dist: typer[all]
Requires-Dist: rich
Requires-Dist: lmdb
Provides-Extra: dev
Requires-Dist: pytest; extra == "dev"
Requires-Dist: pytest-asyncio; extra == "dev"
Requires-Dist: ruff; extra == "dev"
Requires-Dist: mypy; extra == "dev"
Requires-Dist: bandit; extra == "dev"
Requires-Dist: build; extra == "dev"
Requires-Dist: twine; extra == "dev"
Dynamic: license-file
